LSHkRepresentatives/ClusteringAlgorithm.py
LSHkRepresentatives/DILCA.py
LSHkRepresentatives/LSH.py
LSHkRepresentatives/LSHkPrototypes.py
LSHkRepresentatives/LSHkRepresentatives.py
LSHkRepresentatives/LSHkRepresentatives_Full.py
LSHkRepresentatives/MathUtils.py
LSHkRepresentatives/Measure.py
LSHkRepresentatives/MeasureManager.py
LSHkRepresentatives/SimpleHashing.py
LSHkRepresentatives/__init__.py
lshkrepresentatives-1.2.3.dist-info/LICENSE
lshkrepresentatives-1.2.3.dist-info/METADATA
lshkrepresentatives-1.2.3.dist-info/WHEEL
lshkrepresentatives-1.2.3.dist-info/top_level.txt
lshkrepresentatives-1.2.3.dist-info/RECORD
