Metadata-Version: 2.1
Name: lshkrepresentatives
Version: 1.2.3
Summary: LSH-k-Representatives: Mixed categorial and numerical (ordinal and nonordinal) data clustering algorithm algorithm
Home-page: https://github.com/nmtoan91/lshkrepresentatives
Author: nmtoan91
Author-email: toan_stt@yahoo.com
Classifier: Programming Language :: Python :: 3
Classifier: License :: OSI Approved :: MIT License
Classifier: Operating System :: OS Independent
Requires-Python: >=3.6
License-File: LICENSE
